verilog/register_file.v
// Solix-16 Register File
// 8 general-purpose registers (r0-r7) + 3 special registers (SP, PC, FLAGS)
// Total: 11 registers, each 16-bit

module register_file(
    input clk,                  // Clock signal
    input rst,                  // Reset signal (active high)
    
    // Read ports (dual read for ALU operations)
    input [3:0] rs_addr,        // Source register 1 address
    input [3:0] rt_addr,        // Source register 2 address
    output [15:0] rs_data,      // Source register 1 data
    output [15:0] rt_data,      // Source register 2 data
    
    // Write port
    input wr_en,                // Write enable
    input [3:0] rd_addr,        // Destination register address
    input [15:0] rd_data,       // Data to write
    
    // Special register access
    output [15:0] pc_out,       // Program counter output
    output [15:0] sp_out,       // Stack pointer output
    output [15:0] flags_out,    // Flags register output
    input pc_wr,                // PC write enable
    input sp_wr,                // SP write enable
    input flags_wr,             // FLAGS write enable
    input [15:0] pc_in,         // PC input
    input [15:0] sp_in,         // SP input
    input [15:0] flags_in       // FLAGS input
);

// Register array: 11 x 16-bit registers
reg [15:0] registers [0:10];

// Register addresses
parameter R0 = 4'd0;
parameter R1 = 4'd1;
parameter R2 = 4'd2;
parameter R3 = 4'd3;
parameter R4 = 4'd4;
parameter R5 = 4'd5;
parameter R6 = 4'd6;
parameter R7 = 4'd7;
parameter SP = 4'd8;
parameter PC = 4'd9;
parameter FLAGS = 4'd10;

// Asynchronous read (combinational)
assign rs_data = registers[rs_addr];
assign rt_data = registers[rt_addr];

// Special register outputs
assign pc_out = registers[PC];
assign sp_out = registers[SP];
assign flags_out = registers[FLAGS];

// Synchronous write with D flip-flops
always @(posedge clk or posedge rst) begin
    if (rst) begin
        // Reset all registers to 0
        registers[0] <= 16'h0000;
        registers[1] <= 16'h0000;
        registers[2] <= 16'h0000;
        registers[3] <= 16'h0000;
        registers[4] <= 16'h0000;
        registers[5] <= 16'h0000;
        registers[6] <= 16'h0000;
        registers[7] <= 16'h0000;
        registers[8] <= 16'h0000;  // SP
        registers[9] <= 16'h0000;  // PC
        registers[10] <= 16'h0000; // FLAGS
    end
    else begin
        // Write to general-purpose registers
        if (wr_en && rd_addr <= 4'd7) begin
            registers[rd_addr] <= rd_data;
        end
        
        // Write to special registers (independent control)
        if (pc_wr) begin
            registers[PC] <= pc_in;
        end
        
        if (sp_wr) begin
            registers[SP] <= sp_in;
        end
        
        if (flags_wr) begin
            registers[FLAGS] <= flags_in;
        end
    end
end

endmodule

verilog/register_file_tb.v
// Testbench for Solix-16 Register File
`timescale 1ns/1ps

module register_file_tb;

// Clock and reset
reg clk;
reg rst;

// Read ports
reg [3:0] rs_addr;
reg [3:0] rt_addr;
wire [15:0] rs_data;
wire [15:0] rt_data;

// Write port
reg wr_en;
reg [3:0] rd_addr;
reg [15:0] rd_data;

// Special registers
wire [15:0] pc_out;
wire [15:0] sp_out;
wire [15:0] flags_out;
reg pc_wr;
reg sp_wr;
reg flags_wr;
reg [15:0] pc_in;
reg [15:0] sp_in;
reg [15:0] flags_in;

// Instantiate register file
register_file uut (
    .clk(clk),
    .rst(rst),
    .rs_addr(rs_addr),
    .rt_addr(rt_addr),
    .rs_data(rs_data),
    .rt_data(rt_data),
    .wr_en(wr_en),
    .rd_addr(rd_addr),
    .rd_data(rd_data),
    .pc_out(pc_out),
    .sp_out(sp_out),
    .flags_out(flags_out),
    .pc_wr(pc_wr),
    .sp_wr(sp_wr),
    .flags_wr(flags_wr),
    .pc_in(pc_in),
    .sp_in(sp_in),
    .flags_in(flags_in)
);

// Clock generation (10ns period = 100MHz)
initial begin
    clk = 0;
    forever #5 clk = ~clk;
end

// Test sequence
initial begin
    $display("=== Solix-16 Register File Testbench ===\n");
    
    // Initialize signals
    rst = 1;
    wr_en = 0;
    rd_addr = 0;
    rd_data = 0;
    rs_addr = 0;
    rt_addr = 0;
    pc_wr = 0;
    sp_wr = 0;
    flags_wr = 0;
    pc_in = 0;
    sp_in = 0;
    flags_in = 0;
    
    // Wait for reset
    #10;
    rst = 0;
    #10;
    
    $display("Test 1: Reset verification");
    $display("  All registers should be 0");
    rs_addr = 4'd0; #1;
    if (rs_data == 16'h0000) $display("  r0 = 0x%04h ✓", rs_data);
    else $display("  r0 = 0x%04h ✗ (expected 0x0000)", rs_data);
    
    rs_addr = 4'd7; #1;
    if (rs_data == 16'h0000) $display("  r7 = 0x%04h ✓", rs_data);
    else $display("  r7 = 0x%04h ✗ (expected 0x0000)", rs_data);
    
    if (pc_out == 16'h0000 && sp_out == 16'h0000 && flags_out == 16'h0000)
        $display("  PC, SP, FLAGS = 0 ✓\n");
    else
        $display("  Special registers not zero ✗\n");
    
    // Test 2: Write to general-purpose registers
    $display("Test 2: Writing to general-purpose registers");
    @(posedge clk);
    wr_en = 1;
    rd_addr = 4'd1;
    rd_data = 16'h1234;
    @(posedge clk);
    wr_en = 0;
    #1;
    rs_addr = 4'd1;
    #1;
    if (rs_data == 16'h1234) $display("  r1 = 0x%04h ✓", rs_data);
    else $display("  r1 = 0x%04h ✗ (expected 0x1234)", rs_data);
    
    @(posedge clk);
    wr_en = 1;
    rd_addr = 4'd3;
    rd_data = 16'hABCD;
    @(posedge clk);
    wr_en = 0;
    #1;
    rs_addr = 4'd3;
    #1;
    if (rs_data == 16'hABCD) $display("  r3 = 0x%04h ✓\n", rs_data);
    else $display("  r3 = 0x%04h ✗ (expected 0xABCD)\n", rs_data);
    
    // Test 3: Dual read ports
    $display("Test 3: Simultaneous dual read");
    rs_addr = 4'd1;
    rt_addr = 4'd3;
    #1;
    if (rs_data == 16'h1234 && rt_data == 16'hABCD)
        $display("  rs=0x%04h, rt=0x%04h ✓\n", rs_data, rt_data);
    else
        $display("  rs=0x%04h, rt=0x%04h ✗\n", rs_data, rt_data);
    
    // Test 4: Write all registers
    $display("Test 4: Writing to all general-purpose registers");
    wr_en = 1;
    for (integer i = 0; i < 8; i = i + 1) begin
        @(posedge clk);
        rd_addr = i;
        rd_data = 16'h0100 + i;
    end
    @(posedge clk);
    wr_en = 0;
    
    // Verify all writes
    for (integer i = 0; i < 8; i = i + 1) begin
        rs_addr = i;
        #1;
        if (rs_data == (16'h0100 + i))
            $display("  r%0d = 0x%04h ✓", i, rs_data);
        else
            $display("  r%0d = 0x%04h ✗ (expected 0x%04h)", i, rs_data, 16'h0100 + i);
    end
    $display("");
    
    // Test 5: PC write
    $display("Test 5: Program Counter (PC) operations");
    @(posedge clk);
    pc_wr = 1;
    pc_in = 16'h0100;
    @(posedge clk);
    pc_wr = 0;
    #1;
    if (pc_out == 16'h0100) $display("  PC = 0x%04h ✓", pc_out);
    else $display("  PC = 0x%04h ✗ (expected 0x0100)", pc_out);
    
    // Increment PC
    @(posedge clk);
    pc_wr = 1;
    pc_in = pc_out + 1;
    @(posedge clk);
    pc_wr = 0;
    #1;
    if (pc_out == 16'h0101) $display("  PC++ = 0x%04h ✓\n", pc_out);
    else $display("  PC++ = 0x%04h ✗ (expected 0x0101)\n", pc_out);
    
    // Test 6: SP write
    $display("Test 6: Stack Pointer (SP) operations");
    @(posedge clk);
    sp_wr = 1;
    sp_in = 16'hFFFF;
    @(posedge clk);
    sp_wr = 0;
    #1;
    if (sp_out == 16'hFFFF) $display("  SP = 0x%04h ✓", sp_out);
    else $display("  SP = 0x%04h ✗ (expected 0xFFFF)", sp_out);
    
    // Decrement SP (stack grows down)
    @(posedge clk);
    sp_wr = 1;
    sp_in = sp_out - 1;
    @(posedge clk);
    sp_wr = 0;
    #1;
    if (sp_out == 16'hFFFE) $display("  SP-- = 0x%04h ✓\n", sp_out);
    else $display("  SP-- = 0x%04h ✗ (expected 0xFFFE)\n", sp_out);
    
    // Test 7: FLAGS write
    $display("Test 7: Flags register operations");
    @(posedge clk);
    flags_wr = 1;
    flags_in = 16'h000F;  // Z=1, N=1, C=1, O=1
    @(posedge clk);
    flags_wr = 0;
    #1;
    if (flags_out == 16'h000F) $display("  FLAGS = 0x%04h ✓\n", flags_out);
    else $display("  FLAGS = 0x%04h ✗ (expected 0x000F)\n", flags_out);
    
    // Test 8: Simultaneous operations
    $display("Test 8: Simultaneous write and read");
    @(posedge clk);
    wr_en = 1;
    rd_addr = 4'd5;
    rd_data = 16'h5555;
    rs_addr = 4'd3;
    rt_addr = 4'd5;  // Read old value
    #1;
    if (rt_data != 16'h5555)
        $display("  Read before write: rt=0x%04h ✓", rt_data);
    else
        $display("  Read before write: rt=0x%04h (unexpected)", rt_data);
    
    @(posedge clk);
    wr_en = 0;
    #1;
    rt_addr = 4'd5;
    #1;
    if (rt_data == 16'h5555)
        $display("  Read after write: rt=0x%04h ✓\n", rt_data);
    else
        $display("  Read after write: rt=0x%04h ✗\n", rt_data);
    
    // Test 9: Reset during operation
    $display("Test 9: Reset during operation");
    @(posedge clk);
    rst = 1;
    @(posedge clk);
    rst = 0;
    #1;
    rs_addr = 4'd1;
    rt_addr = 4'd3;
    #1;
    if (rs_data == 16'h0000 && rt_data == 16'h0000 && 
        pc_out == 16'h0000 && sp_out == 16'h0000)
        $display("  All registers cleared ✓\n");
    else
        $display("  Reset failed ✗\n");
    
    $display("===========================================");
    $display("All tests completed!");
    $display("===========================================\n");
    
    #50;
    $finish;
end

// Optional: Dump waveform
initial begin
    $dumpfile("register_file.vcd");
    $dumpvars(0, register_file_tb);
end

endmodule

verilog/register_file.vcd
$date
	Thu Nov 20 14:07:21 2025
$end
$version
	Icarus Verilog
$end
$timescale
	1ps
$end
$scope module register_file_tb $end
$var wire 16 ! sp_out [15:0] $end
$var wire 16 " rt_data [15:0] $end
$var wire 16 # rs_data [15:0] $end
$var wire 16 $ pc_out [15:0] $end
$var wire 16 % flags_out [15:0] $end
$var reg 1 & clk $end
$var reg 16 ' flags_in [15:0] $end
$var reg 1 ( flags_wr $end
$var reg 16 ) pc_in [15:0] $end
$var reg 1 * pc_wr $end
$var reg 4 + rd_addr [3:0] $end
$var reg 16 , rd_data [15:0] $end
$var reg 4 - rs_addr [3:0] $end
$var reg 1 . rst $end
$var reg 4 / rt_addr [3:0] $end
$var reg 16 0 sp_in [15:0] $end
$var reg 1 1 sp_wr $end
$var reg 1 2 wr_en $end
$scope module uut $end
$var wire 1 & clk $end
$var wire 16 3 flags_in [15:0] $end
$var wire 16 4 flags_out [15:0] $end
$var wire 1 ( flags_wr $end
$var wire 16 5 pc_in [15:0] $end
$var wire 16 6 pc_out [15:0] $end
$var wire 1 * pc_wr $end
$var wire 4 7 rd_addr [3:0] $end
$var wire 16 8 rd_data [15:0] $end
$var wire 4 9 rs_addr [3:0] $end
$var wire 16 : rs_data [15:0] $end
$var wire 1 . rst $end
$var wire 4 ; rt_addr [3:0] $end
$var wire 16 < rt_data [15:0] $end
$var wire 16 = sp_in [15:0] $end
$var wire 16 > sp_out [15:0] $end
$var wire 1 1 sp_wr $end
$var wire 1 2 wr_en $end
$var parameter 4 ? FLAGS $end
$var parameter 4 @ PC $end
$var parameter 4 A R0 $end
$var parameter 4 B R1 $end
$var parameter 4 C R2 $end
$var parameter 4 D R3 $end
$var parameter 4 E R4 $end
$var parameter 4 F R5 $end
$var parameter 4 G R6 $end
$var parameter 4 H R7 $end
$var parameter 4 I SP $end
$upscope $end
$scope begin $ivl_for_loop0 $end
$var integer 32 J i [31:0] $end
$upscope $end
$scope begin $ivl_for_loop1 $end
$var integer 32 K i [31:0] $end
$upscope $end
$upscope $end
$enddefinitions $end
$comment Show the parameter values. $end
$dumpall
b1000 I
b111 H
b110 G
b101 F
b100 E
b11 D
b10 C
b1 B
b0 A
b1001 @
b1010 ?
$end
#0
$dumpvars
bx K
bx J
b0 >
b0 =
b0 <
b0 ;
b0 :
b0 9
b0 8
b0 7
b0 6
b0 5
b0 4
b0 3
02
01
b0 0
b0 /
1.
b0 -
b0 ,
b0 +
0*
b0 )
0(
b0 '
0&
b0 %
b0 $
b0 #
b0 "
b0 !
$end
#5000
1&
#10000
0&
0.
#15000
1&
#20000
0&
#21000
b111 -
b111 9
#25000
b1001000110100 ,
b1001000110100 8
b1 +
b1 7
12
1&
#30000
0&
#35000
02
1&
#36000
b1001000110100 #
b1001000110100 :
b1 -
b1 9
#40000
0&
#45000
b1010101111001101 ,
b1010101111001101 8
b11 +
b11 7
12
1&
#50000
0&
#55000
02
1&
#56000
b1010101111001101 #
b1010101111001101 :
b11 -
b11 9
#57000
b1010101111001101 "
b1010101111001101 <
b11 /
b11 ;
b1001000110100 #
b1001000110100 :
b1 -
b1 9
#58000
b0 J
12
#60000
0&
#65000
b1 J
b100000000 ,
b100000000 8
b0 +
b0 7
1&
#70000
0&
#75000
b100000001 #
b100000001 :
b10 J
b100000001 ,
b100000001 8
b1 +
b1 7
1&
#80000
0&
#85000
b11 J
b100000010 ,
b100000010 8
b10 +
b10 7
1&
#90000
0&
#95000
b100000011 "
b100000011 <
b100 J
b100000011 ,
b100000011 8
b11 +
b11 7
1&
#100000
0&
#105000
b101 J
b100000100 ,
b100000100 8
b100 +
b100 7
1&
#110000
0&
#115000
b110 J
b100000101 ,
b100000101 8
b101 +
b101 7
1&
#120000
0&
#125000
b111 J
b100000110 ,
b100000110 8
b110 +
b110 7
1&
#130000
0&
#135000
b1000 J
b100000111 ,
b100000111 8
b111 +
b111 7
1&
#140000
0&
#145000
b100000000 #
b100000000 :
b0 -
b0 9
b0 K
02
1&
#146000
b100000001 #
b100000001 :
b1 -
b1 9
b1 K
#147000
b100000010 #
b100000010 :
b10 -
b10 9
b10 K
#148000
b100000011 #
b100000011 :
b11 -
b11 9
b11 K
#149000
b100000100 #
b100000100 :
b100 -
b100 9
b100 K
#150000
b100000101 #
b100000101 :
b101 -
b101 9
b101 K
0&
#151000
b100000110 #
b100000110 :
b110 -
b110 9
b110 K
#152000
b100000111 #
b100000111 :
b111 -
b111 9
b111 K
#153000
b1000 K
#155000
b100000000 $
b100000000 6
b100000000 )
b100000000 5
1*
1&
#160000
0&
#165000
0*
1&
#170000
0&
#175000
b100000001 $
b100000001 6
b100000001 )
b100000001 5
1*
1&
#180000
0&
#185000
0*
1&
#190000
0&
#195000
b1111111111111111 !
b1111111111111111 >
b1111111111111111 0
b1111111111111111 =
11
1&
#200000
0&
#205000
01
1&
#210000
0&
#215000
b1111111111111110 !
b1111111111111110 >
b1111111111111110 0
b1111111111111110 =
11
1&
#220000
0&
#225000
01
1&
#230000
0&
#235000
b1111 %
b1111 4
b1111 '
b1111 3
1(
1&
#240000
0&
#245000
0(
1&
#250000
0&
#255000
b101010101010101 "
b101010101010101 <
b101 /
b101 ;
b100000011 #
b100000011 :
b11 -
b11 9
b101010101010101 ,
b101010101010101 8
b101 +
b101 7
12
1&
#260000
0&
#265000
02
1&
#270000
0&
#275000
b0 %
b0 4
b0 $
b0 6
b0 !
b0 >
b0 "
b0 <
b0 #
b0 :
1.
1&
#280000
0&
#285000
0.
1&
#286000
b11 /
b11 ;
b1 -
b1 9
